epi2hit/__init__.py
epi2hit/cli.py
epi2hit/core.py
epi2hit-0.1.2.dist-info/METADATA
epi2hit-0.1.2.dist-info/WHEEL
epi2hit-0.1.2.dist-info/top_level.txt
epi2hit-0.1.2.dist-info/RECORD
