Metadata-Version: 2.4
Name: epi2hit
Version: 0.1.2
Summary: Pipeline for integrative methylation / expression analysis and eCpG detection
Author: Daria Kiriy
Requires-Python: >=3.8
Requires-Dist: numpy
Requires-Dist: pandas
Requires-Dist: pyBigWig
Requires-Dist: seaborn
Requires-Dist: tqdm
Requires-Dist: matplotlib
Requires-Dist: scikit-learn
Requires-Dist: statannot
Requires-Dist: statsmodels
Requires-Dist: scipy
Requires-Dist: joblib
Requires-Dist: plotnine
Requires-Dist: pybedtools
